gzhutils-1.5.2.dist-info/LICENSE
gzhutils-1.5.2.dist-info/METADATA
gzhutils-1.5.2.dist-info/RECORD
gzhutils-1.5.2.dist-info/top_level.txt
gzhutils-1.5.2.dist-info/WHEEL
gzhutils/_printf.cpython-312-x86_64-linux-gnu.so
gzhutils/logging.py
gzhutils/__init__.py
gzhutils/typing.py
gzhutils/miscellaneous.py
gzhutils/_printf.pyi
gzhutils/_printfmodule.c
gzhutils/path.py
gzhutils/cd_root_add_src.py
gzhutils/ipython.py
gzhutils/visualization/draw_funcs.py
gzhutils/visualization/__init__.py
gzhutils/visualization/utils.py
gzhutils/visualization/options_context.py
