Metadata-Version: 2.1
Name: gzhutils
Version: 1.5.2
Summary: Utility package for myself
Author-email: rkzhai <rkzhai7@gmail.com>
Project-URL: Homepage, https://github.com/rk-terence/gzhutils
Project-URL: Bug Tracker, https://github.com/rk-terence/gzhutils/issues
Classifier: Programming Language :: Python :: 3.12
Classifier: License :: OSI Approved :: MIT License
Classifier: Operating System :: OS Independent
Classifier: Programming Language :: Python :: Implementation :: CPython
Requires-Python: >=3.12
License-File: LICENSE
Provides-Extra: vis
Requires-Dist: matplotlib >=3.8.2 ; extra == 'vis'
Requires-Dist: numpy >=1.26.2 ; extra == 'vis'
